Metadata-Version: 2.1
Name: branches
Version: 0.1.1
Summary: A pure-Python replacement for tree
Home-page: UNKNOWN
Author: douglas.duhaime@gmail.com
Author-email: douglas.duhaime@gmail.com
License: MIT
Platform: UNKNOWN
Classifier: License :: OSI Approved :: MIT License
Classifier: Programming Language :: Python :: 3
Classifier: Programming Language :: Python :: 3.7
Classifier: Programming Language :: Python :: 3.8
Classifier: Programming Language :: Python :: 3.9
Classifier: Programming Language :: Python :: Implementation :: CPython
